{"docs\\camanis\\lemmings_main_dat_file_format.md":{"md":3,"code":0,"terms":["mask","draw"]},"js\\xbrz\\scalers\\Blender.js":{"md":0,"code":6,"terms":["mask","draw"]},"js\\xbrz\\xbrz.js":{"md":0,"code":3,"terms":["mask","draw"]},"js\\DisplayImage.js":{"md":0,"code":8,"terms":["mask","draw"]},"js\\BaseImageInfo.js":{"md":0,"code":3,"terms":["mask","draw"]},"js\\MaskList.js":{"md":0,"code":2,"terms":["mask","draw"]},"js\\Mask.js":{"md":0,"code":2,"terms":["mask","draw"]},"js\\MaskProvider.js":{"md":0,"code":2,"terms":["mask","draw"]},"js\\ActionBaseSystem.js":{"md":0,"code":3,"terms":["mask","draw"]},"js\\ActionCountdownSystem.js":{"md":0,"code":2,"terms":["mask","draw"]},"js\\ActionMineSystem.js":{"md":0,"code":2,"terms":["mask","draw"]},"js\\SolidLayer.js":{"md":0,"code":2,"terms":["mask","draw"]},"js\\ActionBashSystem.js":{"md":0,"code":2,"terms":["mask","draw"]},"js\\Frame.js":{"md":0,"code":2,"terms":["mask","draw"]},"js\\ActionExplodingSystem.js":{"md":0,"code":2,"terms":["mask","draw"]},"js\\Level.js":{"md":0,"code":1,"terms":["mask"]},"js\\MaskTypes.js":{"md":0,"code":1,"terms":["mask"]},"docs\\reading-list\\particle-handling.md":{"md":2,"code":0,"terms":["mask","draw"]},"js\\GameGui.js":{"md":0,"code":1,"terms":["mask","draw"]},"js\\DrawProperties.js":{"md":0,"code":1,"terms":["mask","draw"]}}
