{"docs\\camanis\\lemmings_2_level_file_format.txt":{"md":4,"code":0,"terms":["map","object","t","app"]},"docs\\camanis\\lemmings_2_bitmap_file_format_l2bitmap.md":{"md":3,"code":0,"terms":["map","object"]},"docs\\camanis\\lemmings_vgagrx_dat_groundxo_dat_file_format.md":{"md":1,"code":0,"terms":["map","object"]},"js\\ObjectManager.js":{"md":0,"code":2,"terms":["map","object"]},"js\\MapObject.js":{"md":0,"code":1,"terms":["map","object"]},"js\\ActionBaseSystem.js":{"md":0,"code":1,"terms":["map","object"]},"js\\FileProvider.js":{"md":0,"code":1,"terms":["map","object"]},"docs\\camanis\\lemmings_2_save_file_format.txt":{"md":2,"code":0,"terms":["t","app"]},"docs\\camanis\\lemmings_2_style_file_format_l2gfx.txt":{"md":6,"code":0,"terms":["t","app"]},"docs\\camanis\\lemmings_2_save_file_format.md":{"md":2,"code":0,"terms":["t","app"]},"docs\\exporting-sprites.md":{"md":2,"code":0,"terms":["t","app"]},"docs\\level-file-format.md":{"md":2,"code":0,"terms":["t","app"]},"js\\CommandSelectSkill.js":{"md":0,"code":7,"terms":["t","app"]},"js\\Trigger.js":{"md":0,"code":2,"terms":["t","app"]},"js\\GameTimer.js":{"md":0,"code":2,"terms":["t","app"]},"README.md":{"md":1,"code":0,"terms":["t","app"]},"docs\\camanis\\lemmings_2_level_file_format.md":{"md":2,"code":0,"terms":["t","app"]},"js\\LemmingManager.js":{"md":0,"code":1,"terms":["t","app"]},"js\\CrosshairCursor.js":{"md":0,"code":1,"terms":["t","app"]},"js\\Stage.js":{"md":0,"code":1,"terms":["t","app"]},"js\\xbrz\\scalers\\Blender.js":{"md":0,"code":2,"terms":["t","app"]},"js\\L2ssSpriteDecoder.js":{"md":0,"code":2,"terms":["t","app"]},"js\\vendor\\hqx\\squooshhqx.js":{"md":0,"code":1,"terms":["t","app"]},"js\\vendor\\hqx\\index.js":{"md":0,"code":1,"terms":["t","app"]}}
