{"README.md":{"md":1,"code":0,"terms":["bench","sequence"]},".agentInfo/index-detailed.md":{"md":1,"code":0,"terms":["bench","sequence"]},".agentInfo/notes/overview.md":{"md":1,"code":0,"terms":["bench","sequence"]},".agentInfo/notes/game-view.md":{"md":1,"code":0,"terms":["bench","sequence"]},".agentInfo/index.md":{"md":1,"code":0,"terms":["bench","sequence"]},".agentInfo/notes/bench-mode-docs.md":{"md":1,"code":0,"terms":["bench","sequence"]},".agentInfo/notes/bench-mode.md":{"md":1,"code":0,"terms":["bench","sequence"]},".agentInfo/notes/bench-speed-adjust.md":{"md":1,"code":0,"terms":["bench","sequence"]},".agentInfo/notes/norm-tick-count-removal.md":{"md":1,"code":0,"terms":["bench","sequence"]},".agentInfo/notes/pause-overlay.md":{"md":1,"code":0,"terms":["bench","sequence"]},".agentInfo/notes/test-bench-speed-adjust.md":{"md":1,"code":0,"terms":["bench","sequence"]},".agentInfo/notes/test-coverage.md":{"md":1,"code":0,"terms":["bench","sequence"]},"CHANGELOG.md":{"md":1,"code":0,"terms":["bench","sequence"]},"docs/compression-format.md":{"md":1,"code":0,"terms":["bench","sequence"]},"js/GameView.js":{"md":0,"code":1,"terms":["bench","sequence"]},"test/bench-sequence.test.js":{"md":0,"code":1,"terms":["bench","sequence"]},"js/GameTimer.js":{"md":0,"code":1,"terms":["bench","sequence"]},"js/LemmingManager.js":{"md":0,"code":1,"terms":["bench","sequence"]},".searchMetrics~HEAD":{"md":0,"code":1,"terms":["bench","sequence"]},"js/GameGui.js":{"md":0,"code":1,"terms":["bench","sequence"]},"test/gameview.helpers.test.js":{"md":0,"code":1,"terms":["bench","sequence"]},"js/Game.js":{"md":0,"code":1,"terms":["bench","sequence"]},"js/GameVictoryCondition.js":{"md":0,"code":1,"terms":["bench","sequence"]},"test/bench-no-end.test.js":{"md":0,"code":1,"terms":["bench","sequence"]},"test/bench-speed-adjust.test.js":{"md":0,"code":1,"terms":["bench","sequence"]},"test/bench-tps.test.js":{"md":0,"code":1,"terms":["bench","sequence"]},"test/gamegui.test.js":{"md":0,"code":1,"terms":["bench","sequence"]},"test/gametimer.test.js":{"md":0,"code":1,"terms":["bench","sequence"]},"test/gameview.suspendWithColor.test.js":{"md":0,"code":1,"terms":["bench","sequence"]},"test/getNearestLemming.test.js":{"md":0,"code":1,"terms":["bench","sequence"]},"test/lemming.test.js":{"md":0,"code":1,"terms":["bench","sequence"]},"test/lemmingmanager.test.js":{"md":0,"code":1,"terms":["bench","sequence"]}}
